LICENSE
MANIFEST.in
README.md
setup.cfg
setup.py
loopie/__init__.py
loopie.egg-info/PKG-INFO
loopie.egg-info/SOURCES.txt
loopie.egg-info/dependency_links.txt
loopie.egg-info/not-zip-safe
loopie.egg-info/requires.txt
loopie.egg-info/top_level.txt
loopie/core/__init__.py
loopie/core/application.py
loopie/core/main_loop.py
loopie/core/settings.py
loopie/core/base_threads/__init__.py
loopie/core/base_threads/base_exceptions.py
loopie/core/base_threads/base_threads.py
loopie/core/base_threads/default_routines.py
loopie/core/datetime/__init__.py
loopie/core/datetime/datetime.py
loopie/core/json/__init__.py
loopie/core/json/json_encoder.py
loopie/core/json/myjson.py
loopie/core/metaclasses/__init__.py
loopie/core/metaclasses/class_instance_registry.py
loopie/core/metaclasses/singleton.py
loopie/logging/__init__.py
loopie/logging/format_strings.py
loopie/logging/logger_helper.py
loopie/net/__init__.py
loopie/net/api_routes.py
loopie/net/routes.py
loopie/net/web_app.py
loopie/net/wsgiserver.py
loopie/www/favicon.ico
loopie/www/index.html