Metadata-Version: 2.1
Name: loopie
Version: 0.2.3
Summary: A simple python framework for creating a looping application (Service).
Home-page: https://github.com/yaztown/loopie
Author: Yaztown
Author-email: yaztown@gmail.com
License: GPLv3
Download-URL: https://github.com/yaztown/loopie/archive/v0.2.3.tar.gz
Keywords: loopie,loop,looping,mainloop,thread,threading,Pi,Raspberry Pi,RPi
Platform: UNKNOWN
Classifier: Development Status :: 5 - Production/Stable
Classifier: Intended Audience :: Developers
Classifier: Topic :: Software Development :: Build Tools
Classifier: License :: OSI Approved :: GNU General Public License v3 (GPLv3)
Classifier: Programming Language :: Python :: 3
Classifier: Programming Language :: Python :: 3.4
Classifier: Programming Language :: Python :: 3.5
Classifier: Programming Language :: Python :: 3.6
Classifier: Programming Language :: Python :: 3.7
